SOSTOOLSPy/addextrasosvar.py
SOSTOOLSPy/addextrasosvar2.py
SOSTOOLSPy/addmultvar.py
SOSTOOLSPy/collect.py
SOSTOOLSPy/findcommonZ.py
SOSTOOLSPy/findsos.py
SOSTOOLSPy/getconstraint.py
SOSTOOLSPy/getconstraint2.py
SOSTOOLSPy/getequation.py
SOSTOOLSPy/getequation2.py
SOSTOOLSPy/getequationmc.py
SOSTOOLSPy/inconvhull.py
SOSTOOLSPy/ismember.py
SOSTOOLSPy/max_kron.py
SOSTOOLSPy/mon.py
SOSTOOLSPy/monomials.py
SOSTOOLSPy/monomials2.py
SOSTOOLSPy/oldconstructZ.py
SOSTOOLSPy/oldconstructZ2.py
SOSTOOLSPy/polystr.py
SOSTOOLSPy/preprocess.py
SOSTOOLSPy/sortNoRepeat.py
SOSTOOLSPy/sosdecvar.py
SOSTOOLSPy/soseq.py
SOSTOOLSPy/sosgetsol.py
SOSTOOLSPy/sosineq.py
SOSTOOLSPy/sosmatrixineq.py
SOSTOOLSPy/sospolymatrixvar.py
SOSTOOLSPy/sospolyvar.py
SOSTOOLSPy/sosprogram.py
SOSTOOLSPy/sossetobj.py
SOSTOOLSPy/sossolve.py
SOSTOOLSPy/sossolve2.py
SOSTOOLSPy/sossosvar.py
SOSTOOLSPy/sparsemultipart.py
SOSTOOLSPy/useconvhulln.py
SOSTOOLSPy/veryfing.py
SOSPy-0.2.dist-info/METADATA
SOSPy-0.2.dist-info/WHEEL
SOSPy-0.2.dist-info/top_level.txt
SOSPy-0.2.dist-info/RECORD
