Metadata-Version: 2.1
Name: SOSPy
Version: 0.2
Summary: A toolbox for Sum of Squares Problems
Home-page: 
Author: Leonardo TOSO, Giorgio Valmorbida
Author-email: leonardo-felipe.toso@student-cs.fr,giorgio.valmorbida@centralesupelec.fr
License: UNKNOWN
Platform: UNKNOWN
Classifier: Programming Language :: Python :: 3
Classifier: Operating System :: OS Independent
